nonebot_plugin_mai_arcade/__init__.py
nonebot_plugin_mai_arcade/config.py
nonebot_plugin_mai_arcade/services.py
nonebot_plugin_mai_arcade/utils.py
nonebot_plugin_mai_arcade/handlers/__init__.py
nonebot_plugin_mai_arcade/handlers/admin.py
nonebot_plugin_mai_arcade/handlers/alias.py
nonebot_plugin_mai_arcade/handlers/arcade.py
nonebot_plugin_mai_arcade/handlers/count.py
nonebot_plugin_mai_arcade/handlers/maps.py
nonebot_plugin_mai_arcade/handlers/queue.py
nonebot_plugin_mai_arcade-0.2.0.1.dist-info/licenses/LICENSE
nonebot_plugin_mai_arcade-0.2.0.1.dist-info/METADATA
nonebot_plugin_mai_arcade-0.2.0.1.dist-info/WHEEL
nonebot_plugin_mai_arcade-0.2.0.1.dist-info/top_level.txt
nonebot_plugin_mai_arcade-0.2.0.1.dist-info/RECORD
