Metadata-Version: 2.4
Name: nonebot-plugin-mai-arcade
Version: 0.2.0.1
Summary: maimai arcade nonebot2 plugin
Home-page: https://github.com/YuuzukiRin/nonebot_plugin_mai_arcade
Author: YuuzukiRin
Author-email: yuuzukirin@outlook.com
Classifier: Programming Language :: Python :: 3
Classifier: Programming Language :: Python :: 3.8
Classifier: Programming Language :: Python :: 3.9
Classifier: Programming Language :: Python :: 3.10
Classifier: License :: OSI Approved :: MIT License
Classifier: Operating System :: OS Independent
Requires-Python: >=3.8
License-File: LICENSE
Requires-Dist: nonebot2>=2.2.0
Requires-Dist: nonebot-plugin-localstore>=0.7.0
Requires-Dist: nonebot-adapter-onebot>=2.4.4
Requires-Dist: nonebot-plugin-apscheduler>=0.4.0
Requires-Dist: httpx>=0.24.0
Dynamic: author
Dynamic: author-email
Dynamic: classifier
Dynamic: description
Dynamic: description-content-type
Dynamic: home-page
Dynamic: license-file
Dynamic: requires-dist
Dynamic: requires-python
Dynamic: summary
